agent_payment_client/__init__.py
agent_payment_client/client.py
agent_payment_client-0.1.14.dist-info/LICENSE
agent_payment_client-0.1.14.dist-info/METADATA
agent_payment_client-0.1.14.dist-info/WHEEL
agent_payment_client-0.1.14.dist-info/top_level.txt
agent_payment_client-0.1.14.dist-info/RECORD
