Metadata-Version: 2.2
Name: agent-payment-client
Version: 0.1.14
Summary: SDK for AI agents to make payments on merchant websites, make transfters and other kinds of bill payments.
Author-email: Aliyu Alege <aliyualege@gmail.com>
Project-URL: Homepage, https://github.com/ibnahmadcoded/agent-payment-client
Project-URL: Bug Tracker, https://github.com/ibnahmadcoded/agent-payment-client/issues
Classifier: Programming Language :: Python :: 3
Classifier: License :: OSI Approved :: MIT License
Classifier: Operating System :: OS Independent
Requires-Python: >=3.7
License-File: LICENSE
Requires-Dist: aiohttp>=3.11.13
Requires-Dist: cryptography>=44.0.2
Requires-Dist: playwright>=1.50.0
